odoo/addons/base_product_merge/README.rst
odoo/addons/base_product_merge/__init__.py
odoo/addons/base_product_merge/__manifest__.py
odoo/addons/base_product_merge/i18n/base_product_merge.pot
odoo/addons/base_product_merge/i18n/it.po
odoo/addons/base_product_merge/readme/CONFIGURE.md
odoo/addons/base_product_merge/readme/CONTRIBUTORS.md
odoo/addons/base_product_merge/readme/DESCRIPTION.md
odoo/addons/base_product_merge/readme/USAGE.md
odoo/addons/base_product_merge/security/ir.model.access.csv
odoo/addons/base_product_merge/security/res_groups.xml
odoo/addons/base_product_merge/static/description/icon.png
odoo/addons/base_product_merge/static/description/index.html
odoo/addons/base_product_merge/tests/__init__.py
odoo/addons/base_product_merge/tests/test_base_product_merge.py
odoo/addons/base_product_merge/wizard/__init__.py
odoo/addons/base_product_merge/wizard/base_product_merge.py
odoo/addons/base_product_merge/wizard/base_product_merge_view.xml
odoo_addon_base_product_merge-17.0.1.0.0.4.dist-info/METADATA
odoo_addon_base_product_merge-17.0.1.0.0.4.dist-info/WHEEL
odoo_addon_base_product_merge-17.0.1.0.0.4.dist-info/top_level.txt
odoo_addon_base_product_merge-17.0.1.0.0.4.dist-info/RECORD
