Metadata-Version: 2.1
Name: odoo-addon-base_product_merge
Version: 17.0.1.0.0.4
Requires-Python: >=3.10
Requires-Dist: odoo>=17.0a,<17.1dev
Requires-Dist: openupgradelib
Summary: Merge duplicate products
Home-page: https://github.com/OCA/stock-logistics-warehouse
License: AGPL-3
Author: ForgeFlow, Odoo Community Association (OCA)
Author-email: support@odoo-community.org
Classifier: Programming Language :: Python
Classifier: Framework :: Odoo
Classifier: Framework :: Odoo :: 17.0
Classifier: License :: OSI Approved :: GNU Affero General Public License v3
